relari/__init__.py
relari/__main__.py
relari/client.py
relari/clients/__init__.py
relari/clients/custom_metrics.py
relari/clients/datasets.py
relari/clients/evaluations.py
relari/clients/metrics.py
relari/clients/optimizations.py
relari/clients/projects.py
relari/clients/synth.py
relari/clients/usage.py
relari/core/dataset.py
relari/core/exceptions.py
relari/core/type_parser.py
relari/core/types.py
relari/core/utils.py
relari/metrics.py
relari/utils.py
relari-0.2.1.post9.dist-info/METADATA
relari-0.2.1.post9.dist-info/WHEEL
relari-0.2.1.post9.dist-info/entry_points.txt
relari-0.2.1.post9.dist-info/RECORD
